pycoimset/__init__.py
pycoimset/helpers/__init__.py
pycoimset/helpers/functionals.py
pycoimset/logging/__init__.py
pycoimset/logging/tabular.py
pycoimset/solver/__init__.py
pycoimset/solver/penalty/__init__.py
pycoimset/solver/penalty/solver.py
pycoimset/solver/penalty/eval/__init__.py
pycoimset/solver/penalty/eval/component.py
pycoimset/solver/penalty/eval/infeasibility.py
pycoimset/solver/penalty/eval/penalty_grad.py
pycoimset/solver/penalty/eval/penalty_value.py
pycoimset/solver/penalty/eval/update_pen_grad.py
pycoimset/solver/unconstrained/__init__.py
pycoimset/solver/unconstrained/eval.py
pycoimset/solver/unconstrained/solver.py
pycoimset/step/__init__.py
pycoimset/step/steepest_descent.py
pycoimset/typing/__init__.py
pycoimset/typing/functional.py
pycoimset/typing/io.py
pycoimset/typing/solver.py
pycoimset/typing/space.py
pycoimset/util/__init__.py
pycoimset/util/cache.py
pycoimset/util/controlled_eval.py
pycoimset/util/dependency.py
pycoimset/util/input_check.py
pycoimset/util/signals.py
pycoimset/util/weakref.py
pycoimset-0.1.8.dist-info/LICENSE.md
pycoimset-0.1.8.dist-info/METADATA
pycoimset-0.1.8.dist-info/WHEEL
pycoimset-0.1.8.dist-info/top_level.txt
pycoimset-0.1.8.dist-info/RECORD
