Metadata-Version: 2.2
Name: pycoimset
Version: 0.1.8
Summary: Python library for optimization of sets
Author-email: Mirko Hahn <mirhahn@ovgu.de>
License: Apache License
Project-URL: source, https://github.com/mirhahn/pycoimset
Project-URL: issues, https://github.com/mirhahn/pycoimset/issues
Classifier: Programming Language :: Python :: 3
Classifier: License :: OSI Approved :: Apache Software License
Classifier: Operating System :: OS Independent
Requires-Python: >=3.11
License-File: LICENSE.md
Requires-Dist: numpy>=1.26
